NeizaiXiaohaiKuaileNicaiKuaile/README.md
NeizaiXiaohaiKuaileNicaiKuaile/__init__.py
NeizaiXiaohaiKuaileNicaiKuaile/__main__.py
NeizaiXiaohaiKuaileNicaiKuaile/file.epub
NeizaiXiaohaiKuaileNicaiKuaile/index.html
NeizaiXiaohaiKuaileNicaiKuaile/css/__init__.py
NeizaiXiaohaiKuaileNicaiKuaile/css/annotations.css
NeizaiXiaohaiKuaileNicaiKuaile/css/main.css
NeizaiXiaohaiKuaileNicaiKuaile/css/normalize.css
NeizaiXiaohaiKuaileNicaiKuaile/css/popup.css
NeizaiXiaohaiKuaileNicaiKuaile/font/__init__.py
NeizaiXiaohaiKuaileNicaiKuaile/font/fontello.eot
NeizaiXiaohaiKuaileNicaiKuaile/font/fontello.svg
NeizaiXiaohaiKuaileNicaiKuaile/font/fontello.ttf
NeizaiXiaohaiKuaileNicaiKuaile/font/fontello.woff
NeizaiXiaohaiKuaileNicaiKuaile/img/__init__.py
NeizaiXiaohaiKuaileNicaiKuaile/img/annotator-glyph-sprite.png
NeizaiXiaohaiKuaileNicaiKuaile/img/annotator-icon-sprite.png
NeizaiXiaohaiKuaileNicaiKuaile/img/apple-touch-icon.png
NeizaiXiaohaiKuaileNicaiKuaile/img/cancelfullscreen.png
NeizaiXiaohaiKuaileNicaiKuaile/img/close.png
NeizaiXiaohaiKuaileNicaiKuaile/img/fullscreen.png
NeizaiXiaohaiKuaileNicaiKuaile/img/loader.gif
NeizaiXiaohaiKuaileNicaiKuaile/img/menu-icon.png
NeizaiXiaohaiKuaileNicaiKuaile/img/save.png
NeizaiXiaohaiKuaileNicaiKuaile/img/saved.png
NeizaiXiaohaiKuaileNicaiKuaile/img/settings-s.png
NeizaiXiaohaiKuaileNicaiKuaile/img/settings.png
NeizaiXiaohaiKuaileNicaiKuaile/img/star.png
NeizaiXiaohaiKuaileNicaiKuaile/js/__init__.py
NeizaiXiaohaiKuaileNicaiKuaile/js/epub.js
NeizaiXiaohaiKuaileNicaiKuaile/js/epub.min.js
NeizaiXiaohaiKuaileNicaiKuaile/js/epub.min.map
NeizaiXiaohaiKuaileNicaiKuaile/js/hooks.min.js
NeizaiXiaohaiKuaileNicaiKuaile/js/hooks.min.map
NeizaiXiaohaiKuaileNicaiKuaile/js/reader.js
NeizaiXiaohaiKuaileNicaiKuaile/js/reader.js.map
NeizaiXiaohaiKuaileNicaiKuaile/js/reader.min.js
NeizaiXiaohaiKuaileNicaiKuaile/js/reader.min.map
NeizaiXiaohaiKuaileNicaiKuaile/js/hooks/__init__.py
NeizaiXiaohaiKuaileNicaiKuaile/js/hooks/extensions/__init__.py
neizai_xiaohai_kuaile_nicai_kuaile-2022.9.29.0.dist-info/METADATA
neizai_xiaohai_kuaile_nicai_kuaile-2022.9.29.0.dist-info/WHEEL
neizai_xiaohai_kuaile_nicai_kuaile-2022.9.29.0.dist-info/entry_points.txt
neizai_xiaohai_kuaile_nicai_kuaile-2022.9.29.0.dist-info/top_level.txt
neizai_xiaohai_kuaile_nicai_kuaile-2022.9.29.0.dist-info/RECORD
